CHANGELOG.rst
CHANGES.txt
LICENSE
MANIFEST.in
README.rst
development.ini
secret.ini.example
setup.py
github2fedmsg/__init__.py
github2fedmsg/custom_openid.py
github2fedmsg/events.py
github2fedmsg/githubutils.py
github2fedmsg/tests.py
github2fedmsg/traversal.py
github2fedmsg.egg-info/PKG-INFO
github2fedmsg.egg-info/SOURCES.txt
github2fedmsg.egg-info/dependency_links.txt
github2fedmsg.egg-info/entry_points.txt
github2fedmsg.egg-info/not-zip-safe
github2fedmsg.egg-info/requires.txt
github2fedmsg.egg-info/top_level.txt
github2fedmsg/models/__init__.py
github2fedmsg/models/jsonifiable.py
github2fedmsg/scripts/__init__.py
github2fedmsg/scripts/initializedb.py
github2fedmsg/static/favicon.ico
github2fedmsg/static/footerbg.png
github2fedmsg/static/github2fedmsg.css
github2fedmsg/static/github2fedmsg.png
github2fedmsg/static/headerbg.png
github2fedmsg/static/ie6.css
github2fedmsg/static/jquery-1.11.0.min.js
github2fedmsg/static/middlebg.png
github2fedmsg/static/pyramid-small.png
github2fedmsg/static/pyramid.png
github2fedmsg/static/transparent.gif
github2fedmsg/static/bootstrap-3.1.1-fedora/css/bootstrap-theme.css
github2fedmsg/static/bootstrap-3.1.1-fedora/css/bootstrap-theme.css.map
github2fedmsg/static/bootstrap-3.1.1-fedora/css/bootstrap-theme.min.css
github2fedmsg/static/bootstrap-3.1.1-fedora/css/bootstrap.css
github2fedmsg/static/bootstrap-3.1.1-fedora/css/bootstrap.css.map
github2fedmsg/static/bootstrap-3.1.1-fedora/css/bootstrap.min.css
github2fedmsg/static/bootstrap-3.1.1-fedora/fonts/glyphicons-halflings-regular.eot
github2fedmsg/static/bootstrap-3.1.1-fedora/fonts/glyphicons-halflings-regular.svg
github2fedmsg/static/bootstrap-3.1.1-fedora/fonts/glyphicons-halflings-regular.ttf
github2fedmsg/static/bootstrap-3.1.1-fedora/fonts/glyphicons-halflings-regular.woff
github2fedmsg/static/bootstrap-3.1.1-fedora/js/bootstrap.js
github2fedmsg/static/bootstrap-3.1.1-fedora/js/bootstrap.min.js
github2fedmsg/static/messenger-1.4.1/LICENSE
github2fedmsg/static/messenger-1.4.1/css/messenger-spinner.css
github2fedmsg/static/messenger-1.4.1/css/messenger-theme-air.css
github2fedmsg/static/messenger-1.4.1/css/messenger-theme-block.css
github2fedmsg/static/messenger-1.4.1/css/messenger-theme-flat.css
