Metadata-Version: 1.1
Name: github2fedmsg
Version: 0.3.5
Summary: Pubsubhubbub app that rebroadcasts GH events over fedmsg
Home-page: https://github.com/fedora-infra/github2fedmsg
Author: Ralph Bean
Author-email: rbean@redhat.com
License: UNKNOWN
Keywords: web wsgi bfg pylons pyramid
Platform: UNKNOWN
Classifier: Programming Language :: Python
Classifier: Framework :: Pylons
Classifier: Topic :: Internet :: WWW/HTTP
Classifier: Topic :: Internet :: WWW/HTTP :: WSGI :: Application
